vfind-0.4.0.dist-info/METADATA
vfind-0.4.0.dist-info/WHEEL
vfind-0.4.0.dist-info/licenses/LICENSE
vfind/__init__.py
vfind/vfind.cpython-312-x86_64-linux-gnu.so
vfind-0.4.0.dist-info/RECORD
