Metadata-Version: 2.4
Name: vfind
Version: 0.4.0
Requires-Dist: polars>=1.23.0
License-File: LICENSE
Summary: Simple variant finding utilities for NGS data
Keywords: bioinformatics,sequence analysis,NGS,variant finding
Author-email: nsbuitrago <mail@nsbuitrago.xyz>
Requires-Python: >=3.10
Project-URL: Repository, https://github.com/nsbuitrago/vfind
Project-URL: Issues, https://github.com/nsbuitrago/vfind/issues
